human_captcha_client/__init__.py
human_captcha_client/__main__.py
human_captcha_client/api.py
human_captcha_client/auth.py
human_captcha_client/bbox.py
human_captcha_client/grid.py
human_captcha_client/logger.py
human_captcha_client/py.typed
human_captcha_client/utils.py
human_captcha_client-1.0.6.dist-info/METADATA
human_captcha_client-1.0.6.dist-info/WHEEL
human_captcha_client-1.0.6.dist-info/entry_points.txt
human_captcha_client-1.0.6.dist-info/top_level.txt
human_captcha_client-1.0.6.dist-info/RECORD
