Metadata-Version: 2.1
Name: human-captcha-client
Version: 1.0.6
Author-email: Pradish Bijukchhe <pradish@sandbox.com.np>
Project-URL: Homepage, https://github.com/sandbox-pokhara/human-captcha-client
Project-URL: Issues, https://github.com/sandbox-pokhara/human-captcha-client/issues
Classifier: Programming Language :: Python :: 3
Requires-Python: >=3
Requires-Dist: chime
Requires-Dist: httpx
Requires-Dist: pillow
Requires-Dist: ValLib
